{"info": "These are specialized in anti-air capabilities. Compared to my superior stealth ability, it's definitely a poor ability for sure, but I'll have to deal with it first because it can be annoying to other friends.\n\n\n- Harpyia reporting.", "HP": [228, 35], "ATK": [75, 8], "DEF": [176, 6], "AGI": 3.95, "CRT": 4.5, "HIT": 525, "DOD": 3, "resist": [25, 25, 25], "skills": ["Skill_MP_AMG11AA_N_1", "Skill_MP_AMG11AA_N_2", "Skill_MP_AMG11AA_N_3", "Skill_MP_AMG11AA_N_4", "Skill_MP_AMG11AA_SA2_5"]}